rlsp/__init__.py
rlsp/agents/__init__.py
rlsp/agents/agent_helper.py
rlsp/agents/main.py
rlsp/agents/rlsp_agent.py
rlsp/agents/rlsp_ddpg.py
rlsp/envs/__init__.py
rlsp/envs/action_norm_processor.py
rlsp/envs/environment_limits.py
rlsp/envs/gym_env.py
rlsp/envs/simulator_wrapper.py
rlsp/utils/__init__.py
rlsp/utils/constants.py
rlsp/utils/experiment_result.py
rlsp/utils/q_visualizer.py
rlsp/utils/util_functions.py
deepcoord-1.1.1.dist-info/METADATA
deepcoord-1.1.1.dist-info/WHEEL
deepcoord-1.1.1.dist-info/entry_points.txt
deepcoord-1.1.1.dist-info/top_level.txt
deepcoord-1.1.1.dist-info/RECORD
