Metadata-Version: 2.1
Name: deepcoord
Version: 1.1.1
Summary: DeepCoord: Self-Learning Network and Service Coordination Using Deep Reinforcement Learning
Home-page: https://github.com/RealVNF/DeepCoord
Author: RealVNF
License: UNKNOWN
Platform: UNKNOWN
Requires-Python: >=3.6.*
Requires-Dist: click (==7.0)
Requires-Dist: numpy (<1.19,>=1.16.5)
Requires-Dist: keras (==2.2.5)
Requires-Dist: keras-rl (==0.4.2)
Requires-Dist: tensorflow (==1.14.0)
Requires-Dist: cloudpickle (==1.2)
Requires-Dist: gym[atari] (==0.14.0)
Requires-Dist: pandas (==1.0.0)
Requires-Dist: h5py (==2.10)
Requires-Dist: flake8
Requires-Dist: nose2
